textmentations/__init__.py
textmentations/augmentations/__init__.py
textmentations/augmentations/utils.py
textmentations/augmentations/generation/__init__.py
textmentations/augmentations/generation/functional.py
textmentations/augmentations/generation/transforms.py
textmentations/augmentations/generation/_models/kykim-albert-kor-base/config.json
textmentations/augmentations/generation/_models/kykim-albert-kor-base/pytorch_model.bin
textmentations/augmentations/generation/_models/kykim-albert-kor-base/tokenizer_config.json
textmentations/augmentations/generation/_models/kykim-albert-kor-base/vocab.txt
textmentations/augmentations/modification/__init__.py
textmentations/augmentations/modification/functional.py
textmentations/augmentations/modification/transforms.py
textmentations/core/__init__.py
textmentations/core/composition.py
textmentations/core/transforms_interface.py
textmentations/core/utils.py
textmentations/corpora/__init__.py
textmentations/corpora/corpora.py
textmentations/corpora/types.py
textmentations/corpora/utils.py
textmentations/corpora/corpora/stopwords.txt
textmentations/corpora/corpora/wordnet.json
textmentations-1.4.0.dist-info/LICENSE
textmentations-1.4.0.dist-info/METADATA
textmentations-1.4.0.dist-info/WHEEL
textmentations-1.4.0.dist-info/top_level.txt
textmentations-1.4.0.dist-info/RECORD
