Metadata-Version: 2.1
Name: textmentations
Version: 1.4.0
Summary: A Python library for augmenting Korean text.
Home-page: https://github.com/Jaesu26/textmentations
Author: Jaesu Han
Author-email: gkswotn9753@gmail.com
License: MIT
Keywords: text augmentation,text classification
Classifier: Development Status :: 4 - Beta
Classifier: Intended Audience :: Developers
Classifier: Intended Audience :: Science/Research
Classifier: License :: OSI Approved :: MIT License
Classifier: Operating System :: OS Independent
Classifier: Programming Language :: Python
Classifier: Programming Language :: Python :: 3 :: Only
Classifier: Programming Language :: Python :: 3.8
Classifier: Programming Language :: Python :: 3.9
Classifier: Programming Language :: Python :: 3.10
Classifier: Programming Language :: Python :: 3.11
Classifier: Programming Language :: Python :: 3.12
Classifier: Topic :: Software Development :: Libraries :: Python Modules
Requires-Python: >=3.8
License-File: LICENSE
Requires-Dist: albumentations <=1.4.18,>=1.2.1
Requires-Dist: deep-translator ==1.11.4
Requires-Dist: kiwipiepy <1,>=0.19.0
Requires-Dist: numpy >=1.24.4
Requires-Dist: torch >=2.3.1
Requires-Dist: transformers >=4.30.0
Requires-Dist: typing-extensions <5,>=4.9.0
Provides-Extra: tests
Requires-Dist: pytest ; extra == 'tests'
